st_btn_group/__init__.py
st_btn_group/frontend/build/asset-manifest.json
st_btn_group/frontend/build/bootstrap.min.css
st_btn_group/frontend/build/index.html
st_btn_group/frontend/build/precache-manifest.07f06846523900d2ab60f2e7cc851a9b.js
st_btn_group/frontend/build/precache-manifest.0c89546d64cfab9d7def0c81d0d31221.js
st_btn_group/frontend/build/precache-manifest.62164394aa10973a91714ebc0246d024.js
st_btn_group/frontend/build/precache-manifest.f78a46a46fb1beef94e9ff843da2de8d.js
st_btn_group/frontend/build/service-worker.js
st_btn_group/frontend/build/static/js/2.8362967c.chunk.js
st_btn_group/frontend/build/static/js/2.8362967c.chunk.js.LICENSE.txt
st_btn_group/frontend/build/static/js/2.8362967c.chunk.js.map
st_btn_group/frontend/build/static/js/2.9d8196d8.chunk.js
st_btn_group/frontend/build/static/js/2.9d8196d8.chunk.js.LICENSE.txt
st_btn_group/frontend/build/static/js/2.9d8196d8.chunk.js.map
st_btn_group/frontend/build/static/js/main.6b3ab739.chunk.js
st_btn_group/frontend/build/static/js/main.6b3ab739.chunk.js.map
st_btn_group/frontend/build/static/js/main.7ca433ed.chunk.js
st_btn_group/frontend/build/static/js/main.7ca433ed.chunk.js.map
st_btn_group/frontend/build/static/js/main.8f78e7c1.chunk.js
st_btn_group/frontend/build/static/js/main.8f78e7c1.chunk.js.map
st_btn_group/frontend/build/static/js/main.d2098cac.chunk.js
st_btn_group/frontend/build/static/js/main.d2098cac.chunk.js.map
st_btn_group/frontend/build/static/js/runtime-main.6b0b1766.js
st_btn_group/frontend/build/static/js/runtime-main.6b0b1766.js.map
st_bnt_group-0.0.4.dist-info/LICENSE
st_bnt_group-0.0.4.dist-info/METADATA
st_bnt_group-0.0.4.dist-info/WHEEL
st_bnt_group-0.0.4.dist-info/top_level.txt
st_bnt_group-0.0.4.dist-info/RECORD
