Metadata-Version: 2.1
Name: st-bnt-group
Version: 0.0.4
Summary: Streamlit Component for BaseWeb Button Group
Author: 
Author-email: 
Requires-Python: >=3.6
License-File: LICENSE
Requires-Dist: streamlit (>=0.63)
